pyrovider/__init__.py
pyrovider-10.0.6.dist-info/METADATA
pyrovider-10.0.6.dist-info/WHEEL
pyrovider-10.0.6.dist-info/top_level.txt
pyrovider-10.0.6.dist-info/RECORD
