Metadata-Version: 2.1
Name: pyrovider
Version: 10.0.6
Summary: Dependency confiuse Test
Author: shiphero
Author-email: hello@shiphero.com
